fountaincoding/__init__.py
fountaincoding/fountaincoding.py
qrstreamer-0.1.2.data/scripts/qrstreamer.py
qrstreamer-0.1.2.dist-info/LICENSE
qrstreamer-0.1.2.dist-info/METADATA
qrstreamer-0.1.2.dist-info/WHEEL
qrstreamer-0.1.2.dist-info/top_level.txt
qrstreamer-0.1.2.dist-info/RECORD
