Metadata-Version: 2.1
Name: qrstreamer
Version: 0.1.2
Summary: A module for streaming files into QR codes
Home-page: https://github.com/ThePlasmaRailgun/QRStreamer
Author: Finian Blackett
Author-email: spamsuckersunited@gmail.com
License: UNKNOWN
Platform: UNKNOWN
Classifier: Programming Language :: Python :: 3.6
Classifier: License :: OSI Approved :: GNU General Public License v3 (GPLv3)
Classifier: Operating System :: OS Independent
Requires-Dist: qrcode
Requires-Dist: outdated
